fastmcp_transport_ble/__init__.py
fastmcp_transport_ble/constants.py
fastmcp_transport_ble/framing.py
fastmcp_transport_ble/transport.py
fastmcp_transport_ble-0.0.1.dist-info/METADATA
fastmcp_transport_ble-0.0.1.dist-info/WHEEL
fastmcp_transport_ble-0.0.1.dist-info/top_level.txt
fastmcp_transport_ble-0.0.1.dist-info/RECORD
