Metadata-Version: 2.4
Name: fastmcp-transport-ble
Version: 0.0.1
Summary: BLE transport for FastMCP clients.
Keywords: mcp,fastmcp,ble,bluetooth
Classifier: Programming Language :: Python :: 3
Classifier: Programming Language :: Python :: 3 :: Only
Classifier: Programming Language :: Python :: 3.10
Classifier: Programming Language :: Python :: 3.11
Classifier: Programming Language :: Python :: 3.12
Classifier: Programming Language :: Python :: 3.13
Requires-Python: >=3.10
Requires-Dist: anyio
Requires-Dist: bleak
Requires-Dist: fastmcp
Requires-Dist: mcp
Provides-Extra: dev
Requires-Dist: build; extra == "dev"
Requires-Dist: twine; extra == "dev"
